CHANGES.txt
LICENSE.txt
MANIFEST.in
README.txt
buildout.cfg
setup.py
src/p01/__init__.py
src/p01.json.egg-info/PKG-INFO
src/p01.json.egg-info/SOURCES.txt
src/p01.json.egg-info/dependency_links.txt
src/p01.json.egg-info/namespace_packages.txt
src/p01.json.egg-info/not-zip-safe
src/p01.json.egg-info/requires.txt
src/p01.json.egg-info/top_level.txt
src/p01/json/README.txt
src/p01/json/__init__.py
src/p01/json/api.py
src/p01/json/exceptions.py
src/p01/json/proxy.py
src/p01/json/tests.py
src/p01/json/transport.py