Metadata-Version: 2.1
Name: p01.json
Version: 0.7.3
Summary: JSON-RPC proxy using application/json-rpc as default Content-Type
Home-page: http://pypi.python.org/pypi/p01.json
Author: Roger Ineichen, Projekt01 GmbH
Author-email: dev@projekt01.ch
License: ZPL 2.1
Keywords: zope3 z3c p01 json json-rpc rpc
Platform: UNKNOWN
Classifier: Development Status :: 4 - Beta
Classifier: Environment :: Web Environment
Classifier: Intended Audience :: Developers
Classifier: License :: OSI Approved :: Zope Public License
Classifier: Programming Language :: Python
Classifier: Natural Language :: English
Classifier: Operating System :: OS Independent
Classifier: Topic :: Internet :: WWW/HTTP
Classifier: Framework :: Zope3
Provides-Extra: test
